{
  "total_requests": 10,
  "mean_rate": 0.35,
  "users": 10,
  "requests": [
    {
      "start_time": 1757612208.8151624,
      "end_time": 1757612209.9206333,
      "duration": 1.105470895767212,
      "status_code": 200
    },
    {
      "start_time": 1757612262.6364872,
      "end_time": 1757612263.6569715,
      "duration": 1.020484209060669,
      "status_code": 200
    },
    {
      "start_time": 1757612301.1092842,
      "end_time": 1757612302.0763345,
      "duration": 0.967050313949585,
      "status_code": 200
    },
    {
      "start_time": 1757612330.5009124,
      "end_time": 1757612331.4528272,
      "duration": 0.9519147872924805,
      "status_code": 200
    },
    {
      "start_time": 1757612340.3392324,
      "end_time": 1757612346.4442537,
      "duration": 6.105021238327026,
      "status_code": 200
    },
    {
      "start_time": 1757612482.0150347,
      "end_time": 1757612483.0076854,
      "duration": 0.9926507472991943,
      "status_code": 200
    },
    {
      "start_time": 1757612484.2928817,
      "end_time": 1757612485.281742,
      "duration": 0.9888603687286377,
      "status_code": 200
    },
    {
      "start_time": 1757612548.4915583,
      "end_time": 1757612549.561092,
      "duration": 1.0695335865020752,
      "status_code": 200
    },
    {
      "start_time": 1757612628.8275177,
      "end_time": 1757612634.0754886,
      "duration": 5.247970819473267,
      "status_code": 200
    },
    {
      "start_time": 1757612686.3993065,
      "end_time": 1757612687.335203,
      "duration": 0.9358963966369629,
      "status_code": 200
    }
  ]
}